{"configVersion":92,"detailLog":false,"maxLogSize":512,"forceMountData":true,"aggressiveFilter":true,"templates":{"yh黑名单":{"isWhitelist":false,"appList":["com.aistra.hail","world.letsgo.booster.android.pro","com.chunqiu.detector","com.abilvcha.main","wu.keyChain.test","io.github.vvb2060.keyattestation","com.tencent.docs","com.clone.android.dual.space","com.surcumference.fingerprintpay","o.dyoo","top.hookvip.pro","io.github.a13e300.ksuwebui","com.luckyzyx.luckytool","io.github.huskydg.memorydetector","bin.mt.termex","cn.myflv.monitor.noactive","gr.nikolasspyr.integritycheck","com.yxer.packageinstalles","com.yxer.compo.module","io.liankong.riskdetector","com.byxiaorun.detector","com.omarea.vtools","com.henrikherzig.playintegritychecker","com.sukisu.ultra","org.telegram.messenger.web","com.my.televip","github.tornaco.android.thanos","me.hd.wauxv","id.my.pjm.qbcd_okr_dvii","com.guoshi.httpcanary","safe.HMAdetect.demo","com.apocalua.run","JianJie.DK","yezi.com","tornaco.apps.shortx","com.kimchangyoun.rootbeerFresh.sample","wu.Rookie.Detector","icu.nullptr.nativetest","com.oioioioioioioioioioi","xzr.konabess","com.bug.hookvip","com.rcmiku.payload.dumper.compose","com.geektoy.nfctool","com.gamelua.manalua","com.xayah.databackup.premium","com.tsng.hidemyapplist","bin.mt.plus","io.github.nitsuya.donottryaccessibility","wu.Zygisk.Detector","com.haobammmm","com.zhenxi.hunter","me.garfieldhan.holmes","com.youhu.laifu","io.github.vvb2060.magiskdetector","io.github.vvb2060.mahoshojo","com.reveny.nativecheck","chunqiu.safe.detector","chunqiu.keyattestation.safe","org.akanework.checker","com.tsng.applistdetector","com.jmr.myapp4","com.n0n3m4.droidc","com.jc","com.n0n3m4.gcc4droid","com.lingqing.detector","luna.safe.luna","com.mito","com.detect.mt","com.android.nativetest","com.fantasytat.propdor","wu.root.detector","com.n0n3m4.droidsdl","io.github.rabehx.securify","wu.futile.hide","com.android.admin","io.github.a13e300.fusefixer","com.sevtinge.hyperceiler","me.feimeng.vip","me.weishu.kernelsu","lin.xposed","www.netproxy.web.ui","com.raincat.dolby_alpha","com.flass.layoutinspect"]}},"scope":{"icu.nullptr.applistdetector":{"useWhitelist":true,"excludeSystemApps":true,"applyTemplates":[],"extraAppList":[]},"com.hero.sm.android.hero":{"useWhitelist":true,"excludeSystemApps":true,"applyTemplates":[],"extraAppList":[]},"com.hero.sm.m4399":{"useWhitelist":true,"excludeSystemApps":true,"applyTemplates":[],"extraAppList":["com.m4399.gamecenter"]},"com.tgp.autologin":{"useWhitelist":true,"excludeSystemApps":true,"applyTemplates":[],"extraAppList":[]},"com.uhaozu.autoapp":{"useWhitelist":false,"excludeSystemApps":true,"applyTemplates":["yh黑名单"],"extraAppList":[]},"com.xd.xdt":{"useWhitelist":true,"excludeSystemApps":true,"applyTemplates":[],"extraAppList":["com.taptap"]},"com.dalianboyou.uzh":{"useWhitelist":true,"excludeSystemApps":true,"applyTemplates":[],"extraAppList":[]},"com.sankuai.meituan.dispatch.crowdsource":{"useWhitelist":true,"excludeSystemApps":true,"applyTemplates":[],"extraAppList":["com.tencent.mm","com.tencent.mobileqq","com.sankuai.meituan","com.sankuai.meituan.dispatch.crowdsource"]},"com.kotak811mobilebankingapp.instantsavingsupiscanandpayrecharge":{"useWhitelist":true,"excludeSystemApps":true,"applyTemplates":[],"extraAppList":[]},"com.daofeng.zuhaowan":{"useWhitelist":true,"excludeSystemApps":true,"applyTemplates":[],"extraAppList":["com.tencent.tmgp.sgame","com.tencent.mobileqq"]},"com.xubei.shop":{"useWhitelist":true,"excludeSystemApps":true,"applyTemplates":[],"extraAppList":["com.tencent.tmgp.sgame","com.tencent.mobileqq","com.tencent.tmgp.cf","com.tencent.mm","com.tencent.tmgp.pubgmhd"]},"com.tencent.tmgp.sgame":{"useWhitelist":false,"excludeSystemApps":true,"applyTemplates":["yh黑名单"],"extraAppList":[]},"com.tencent.tmgp.pubgmhd":{"useWhitelist":false,"excludeSystemApps":true,"applyTemplates":["yh黑名单"],"extraAppList":[]},"com.youhu.laifu":{"useWhitelist":true,"excludeSystemApps":true,"applyTemplates":[],"extraAppList":[]},"com.duodian.zubajie":{"useWhitelist":true,"excludeSystemApps":true,"applyTemplates":[],"extraAppList":["com.tencent.tmgp.pubgmhd","com.tencent.mobileqq","com.tencent.mm"]},"com.duodian.zuhaobao":{"useWhitelist":true,"excludeSystemApps":true,"applyTemplates":[],"extraAppList":["com.tencent.tmgp.pubgmhd","com.tencent.mm","com.tencent.mobileqq"]},"com.duodian.freehire":{"useWhitelist":true,"excludeSystemApps":true,"applyTemplates":[],"extraAppList":["com.tencent.tmgp.pubgmhd","com.tencent.mm","com.tencent.mobileqq"]},"com.mirui.pxzh":{"useWhitelist":true,"excludeSystemApps":true,"applyTemplates":[],"extraAppList":["com.tencent.tmgp.pubgmhd","com.tencent.mobileqq"]},"com.fantasytat.propdor":{"useWhitelist":true,"excludeSystemApps":true,"applyTemplates":[],"extraAppList":[]},"com.zhenxi.hunter":{"useWhitelist":true,"excludeSystemApps":true,"applyTemplates":[],"extraAppList":[]},"com.uhaozu.app":{"useWhitelist":true,"excludeSystemApps":true,"applyTemplates":[],"extraAppList":[]},"me.garfieldhan.holmes":{"useWhitelist":true,"excludeSystemApps":true,"applyTemplates":[],"extraAppList":[]},"com.tencent.letsgo":{"useWhitelist":true,"excludeSystemApps":true,"applyTemplates":[],"extraAppList":[]},"com.kotak.neo":{"useWhitelist":true,"excludeSystemApps":true,"applyTemplates":[],"extraAppList":[]},"com.xzzq.xiaozhuo":{"useWhitelist":true,"excludeSystemApps":true,"applyTemplates":[],"extraAppList":[]},"com.godevelopers.OprekCek":{"useWhitelist":true,"excludeSystemApps":true,"applyTemplates":[],"extraAppList":[]},"io.liankong.riskdetector":{"useWhitelist":true,"excludeSystemApps":true,"applyTemplates":[],"extraAppList":[]},"com.tencent.tmgp.dfm":{"useWhitelist":false,"excludeSystemApps":true,"applyTemplates":["yh黑名单"],"extraAppList":[]},"com.lingqing.detector":{"useWhitelist":true,"excludeSystemApps":true,"applyTemplates":[],"extraAppList":[]},"wu.hmal.detector":{"useWhitelist":true,"excludeSystemApps":true,"applyTemplates":[],"extraAppList":[]},"com.reveny.nativecheck":{"useWhitelist":true,"excludeSystemApps":true,"applyTemplates":[],"extraAppList":[]},"chunqiu.safe":{"useWhitelist":false,"excludeSystemApps":true,"applyTemplates":["yh黑名单"],"extraAppList":[]},"com.tencent.jkchess":{"useWhitelist":false,"excludeSystemApps":true,"applyTemplates":["yh黑名单"],"extraAppList":[]},"com.byxiaorun.detector":{"useWhitelist":false,"excludeSystemApps":true,"applyTemplates":["yh黑名单"],"extraAppList":[]},"com.OrangeEnvironment.Detector":{"useWhitelist":false,"excludeSystemApps":true,"applyTemplates":["yh黑名单"],"extraAppList":[]},"com.fantasytat.det":{"useWhitelist":false,"excludeSystemApps":true,"applyTemplates":["yh黑名单"],"extraAppList":[]},"com.tsng.applistdetector":{"useWhitelist":false,"excludeSystemApps":true,"applyTemplates":["yh黑名单"],"extraAppList":[]},"io.github.vvb2060.magiskdetector":{"useWhitelist":false,"excludeSystemApps":true,"applyTemplates":["yh黑名单"],"extraAppList":[]},"chunqiu.safe.detector":{"useWhitelist":false,"excludeSystemApps":true,"applyTemplates":["yh黑名单"],"extraAppList":[]},"com.native.check":{"useWhitelist":false,"excludeSystemApps":true,"applyTemplates":["yh黑名单"],"extraAppList":[]},"com.example.myapplication":{"useWhitelist":false,"excludeSystemApps":true,"applyTemplates":["yh黑名单"],"extraAppList":[]},"com.rem01gaming.disclosure":{"useWhitelist":false,"excludeSystemApps":true,"applyTemplates":["yh黑名单"],"extraAppList":[]},"com.larus.nova":{"useWhitelist":false,"excludeSystemApps":true,"applyTemplates":["yh黑名单"],"extraAppList":[]},"com.autonavi.minimap":{"useWhitelist":false,"excludeSystemApps":true,"applyTemplates":["yh黑名单"],"extraAppList":[]},"com.smilingmobile.practice":{"useWhitelist":false,"excludeSystemApps":true,"applyTemplates":["yh黑名单"],"extraAppList":[]},"com.ss.android.ugc.aweme":{"useWhitelist":false,"excludeSystemApps":true,"applyTemplates":["yh黑名单"],"extraAppList":[]},"com.tencent.tmgp.sgamece":{"useWhitelist":false,"excludeSystemApps":true,"applyTemplates":["yh黑名单"],"extraAppList":[]},"com.tencent.mm":{"useWhitelist":false,"excludeSystemApps":true,"applyTemplates":["yh黑名单"],"extraAppList":[]},"com.chaoxing.mobile":{"useWhitelist":false,"excludeSystemApps":true,"applyTemplates":["yh黑名单"],"extraAppList":[]},"com.eg.android.AlipayGphone":{"useWhitelist":false,"excludeSystemApps":true,"applyTemplates":["yh黑名单"],"extraAppList":[]},"com.greenpoint.android.mc10086.activity":{"useWhitelist":false,"excludeSystemApps":true,"applyTemplates":["yh黑名单"],"extraAppList":[]},"com.chinamobile.mcloud":{"useWhitelist":false,"excludeSystemApps":true,"applyTemplates":["yh黑名单"],"extraAppList":[]},"com.tencent.mobileqq":{"useWhitelist":false,"excludeSystemApps":true,"applyTemplates":["yh黑名单"],"extraAppList":[]},"com.jingdong.app.mall":{"useWhitelist":false,"excludeSystemApps":true,"applyTemplates":["yh黑名单"],"extraAppList":[]},"com.smile.gifmaker":{"useWhitelist":false,"excludeSystemApps":true,"applyTemplates":["yh黑名单"],"extraAppList":[]},"com.sankuai.meituan.takeoutnew":{"useWhitelist":false,"excludeSystemApps":true,"applyTemplates":["yh黑名单"],"extraAppList":[]},"com.taobao.taobao":{"useWhitelist":false,"excludeSystemApps":true,"applyTemplates":["yh黑名单"],"extraAppList":[]},"com.taobao.idlefish":{"useWhitelist":false,"excludeSystemApps":true,"applyTemplates":["yh黑名单"],"extraAppList":[]},"cn.com.chsi.chsiapp":{"useWhitelist":false,"excludeSystemApps":true,"applyTemplates":["yh黑名单"],"extraAppList":[]}}}